nexus_api_client/__init__.py
nexus_api_client/api_client.py
nexus_api_client/api_response.py
nexus_api_client/configuration.py
nexus_api_client/exceptions.py
nexus_api_client/py.typed
nexus_api_client/rest.py
nexus_api_client/api/__init__.py
nexus_api_client/api/assets_api.py
nexus_api_client/api/azure_blob_store_api.py
nexus_api_client/api/blob_store_api.py
nexus_api_client/api/capabilities_api.py
nexus_api_client/api/cleanup_policies_api.py
nexus_api_client/api/community_edition_eula_api.py
nexus_api_client/api/components_api.py
nexus_api_client/api/content_selectors_api.py
nexus_api_client/api/data_store_api.py
nexus_api_client/api/email_api.py
nexus_api_client/api/formats_api.py
nexus_api_client/api/instance_configuration_api.py
nexus_api_client/api/lifecycle_api.py
nexus_api_client/api/malicious_risk_on_disk_api.py
nexus_api_client/api/manage_sonatype_http_system_settings_api.py
nexus_api_client/api/manage_sonatype_repository_firewall_configuration_api.py
nexus_api_client/api/monthly_metrics_api.py
nexus_api_client/api/product_licensing_api.py
nexus_api_client/api/read_only_api.py
nexus_api_client/api/reconcile_plan_api.py
nexus_api_client/api/repository_management_api.py
nexus_api_client/api/routing_rules_api.py
nexus_api_client/api/script_api.py
nexus_api_client/api/search_api.py
nexus_api_client/api/security_atlassian_crowd_api.py
nexus_api_client/api/security_certificates_api.py
nexus_api_client/api/security_management_anonymous_access_api.py
nexus_api_client/api/security_management_api.py
nexus_api_client/api/security_management_api_keys_principals_encryption_api.py
nexus_api_client/api/security_management_ldap_api.py
nexus_api_client/api/security_management_privileges_api.py
nexus_api_client/api/security_management_realms_api.py
nexus_api_client/api/security_management_roles_api.py
nexus_api_client/api/security_management_saml_api.py
nexus_api_client/api/security_management_saml_users_api.py
nexus_api_client-3.88.1.dist-info/licenses/LICENSE
nexus_api_client-3.88.1.dist-info/METADATA
nexus_api_client-3.88.1.dist-info/WHEEL
nexus_api_client-3.88.1.dist-info/top_level.txt
nexus_api_client-3.88.1.dist-info/RECORD
