Metadata-Version: 2.4
Name: nexus_api_client
Version: 3.88.1
Summary: Sonatype Nexus Repository Manager
Home-page: 
Author: Sonatype Community Maintainers
Author-email: Sonatype Community Maintainers <community@sonatype.com>
License: Apache-2.0
Project-URL: Repository, https://github.com/sonatype-nexus-community/nexus-repo-api-client
Keywords: OpenAPI,OpenAPI-Generator,Sonatype Nexus Repository Manager
Requires-Python: >=3.9
License-File: LICENSE
Requires-Dist: urllib3<3.0.0,>=2.1.0
Requires-Dist: python-dateutil>=2.8.2
Requires-Dist: pydantic>=2
Requires-Dist: typing-extensions>=4.7.1
Dynamic: author
Dynamic: license-file
